[
  {
    "id": "IMG_2782",
    "question": "Τι επιθήλιο βλέπεις;",
    "answer": "Μονόστιβο πλακώδες επιθήλιο.",
    "category": "Histology"
  },
  {
    "id": "IMG_2783",
    "question": "Τι επιθήλιο βλέπεις;",
    "answer": "Μονόστιβο κυβοειδές επιθήλιο.",
    "category": "Histology"
  },
  {
    "id": "IMG_2784",
    "question": "Τι επιθήλιο βλέπεις;",
    "answer": "Μονόστιβο κυλινδρικό επιθήλιο.",
    "category": "Histology"
  },
  {
    "id": "IMG_2785",
    "question": "Τι επιθήλιο βλέπεις;",
    "answer": "Πολύστιβο πλακώδες επιθήλιο με χαμηλό βαθμό κερατινοποίησης.",
    "category": "Histology"
  },
  {
    "id": "IMG_2786",
    "question": "Τι επιθήλιο βλέπεις;",
    "answer": "Πολύστιβο πλακώδες επιθήλιο με υψηλό βαθμό κερατινοποίησης (επιδερμίδα).",
    "category": "Histology"
  },
  {
    "id": "IMG_2787",
    "question": "Τι επιθήλιο βλέπεις;",
    "answer": "Ψευδοπολύστιβο κροσσωτό επιθήλιο.",
    "category": "Histology"
  },
  {
    "id": "IMG_2788",
    "question": "Τι ιστό βλέπεις;",
    "answer": "Υαλοειδής χόνδρος.",
    "category": "Histology"
  },
  {
    "id": "IMG_2789",
    "question": "Τι ιστό βλέπεις;",
    "answer": "Αδενικό επιθήλιο (αριστερά: εγκάρσια τομή, δεξιά: επιμήκης τομή).",
    "category": "Histology"
  },
  {
    "id": "IMG_2790",
    "question": "Τι ιστό βλέπεις;",
    "answer": "Εγκάρσια τομή αδενικού επιθηλίου.",
    "category": "Histology"
  },
  {
    "id": "IMG_2791",
    "question": "Τι ιστό βλέπεις;",
    "answer": "Επιμήκης τομή αδενικού επιθηλίου.",
    "category": "Histology"
  },
  {
    "id": "IMG_2792",
    "question": "Τι επιθήλιο βλέπεις;",
    "answer": "Μεταβατικό επιθήλιο (ουροθήλιο) σε χαμηλή μεγέθυνση.",
    "category": "Histology"
  },
  {
    "id": "IMG_2793",
    "question": "Τι ιστό βλέπεις;",
    "answer": "Μεταβατικό επιθήλιο (ουροθήλιο) σε υψηλή μεγέθυνση.",
    "category": "Histology"
  },
  {
    "id": "IMG_2794",
    "question": "Τι βλέπεις και τι είναι οι μαύρες ίνες;",
    "answer": "Δικτυωτός συνδετικός ιστός. Οι μαύρες ίνες είναι ίνες ρετικουλίνης. Χρώση με νιτρικό άργυρο.",
    "category": "Histology"
  },
  {
    "id": "IMG_2795",
    "question": "Τι ιστό βλέπεις;",
    "answer": "Μονόχωρος λιπώδης ιστός (λευκό λίπος).",
    "category": "Histology"
  },
  {
    "id": "IMG_2796",
    "question": "Τι ιστό βλέπεις;",
    "answer": "Πυκνός κανονικός συνδετικός ιστός (τένοντας).",
    "category": "Histology"
  },
  {
    "id": "IMG_2797",
    "question": "Τι επιθήλιο βλέπεις;",
    "answer": "Πολύστιβο πλακώδες επιθήλιο με υψηλό βαθμό κερατινοποίησης (επιδερμίδα).",
    "category": "Histology"
  },
  {
    "id": "IMG_2798",
    "question": "Τι ιστό βλέπεις;",
    "answer": "Πυκνός ακανόνιστος συνδετικός ιστός.",
    "category": "Histology"
  },
  {
    "id": "IMG_2799",
    "question": "Τι ιστό βλέπεις; Ονόμασε τις δομές.",
    "answer": "Χαλαρός συνδετικός ιστός. Διακρίνονται ελαστικές ίνες (λεπτές και μαύρες), κολλαγόνες ίνες (ροζ) και πυρήνες ινοβλαστών.",
    "category": "Histology"
  },
  {
    "id": "IMG_2800",
    "question": "Τι δομή βλέπεις και τι είναι η επισημασμένη περιοχή (χρώση Α/Η);",
    "answer": "Αορτή. Η γκρίζα περιοχή αντιστοιχεί σε ελαστικές ίνες.",
    "category": "Histology"
  },
  {
    "id": "IMG_2801",
    "question": "Τι ιστό βλέπεις;",
    "answer": "Ψευδοπολύστιβο κροσσωτό επιθήλιο.",
    "category": "Histology"
  },
  {
    "id": "IMG_2802",
    "question": "Πώς ονομάζεται αυτή η περιοχή;",
    "answer": "Περιχόνδριο.",
    "category": "Histology"
  },
  {
    "id": "IMG_2803",
    "question": "Τι ιστό βλέπεις;",
    "answer": "Ελαστικός χόνδρος, στον οποίο διακρίνεται και το περιχόνδριο.",
    "category": "Histology"
  },
  {
    "id": "IMG_2804",
    "question": "Τι ιστό βλέπεις και πού βρίσκεται;",
    "answer": "Ινώδης χόνδρος, όπως στους μεσοσπονδύλιους δίσκους.",
    "category": "Histology"
  },
  {
    "id": "IMG_2805",
    "question": "Τι ιστό βλέπεις και ποιες δομές υπάρχουν;",
    "answer": "Συμπαγές πεταλιώδες οστό. Διακρίνεται οστεώνας (σύστημα Havers), με τον κεντρικό σωλήνα του Havers και οστικά βοθρία που περιέχουν οστεοκύτταρα.",
    "category": "Histology"
  },
  {
    "id": "IMG_2806",
    "question": "Τι ιστό βλέπεις και ποιες δομές υπάρχουν;",
    "answer": "Δοκιδώδες ή σπογγώδες οστό. Διακρίνονται οστικές δοκίδες και περιοχές με λιπώδη ιστό και μυελό των οστών.",
    "category": "Histology"
  },
  {
    "id": "IMG_2807",
    "question": "Τι είδους οστεοποίηση βλέπεις και σε ποια οστά συμβαίνει;",
    "answer": "Ενδοχόνδρια οστεοποίηση, κυρίως στα μακρά οστά.",
    "category": "Histology"
  },
  {
    "id": "IMG_2808",
    "question": "Τι είδους οστεοποίηση βλέπεις; Ονόμασε τις ζώνες.",
    "answer": "Ενδοχόνδρια οστεοποίηση. Ζώνες: ηρεμίας, πολλαπλασιασμού, υπερτροφίας, ασβεστοποίησης και οστεοποίησης.",
    "category": "Histology"
  },
  {
    "id": "IMG_2809",
    "question": "Τι είδους οστεοποίηση βλέπεις; Ονόμασε την επισημασμένη δομή.",
    "answer": "Ενδομεμβρανώδης οστεοποίηση. Η μπλε δομή είναι οστική δοκίδα.",
    "category": "Histology"
  },
  {
    "id": "IMG_2811",
    "question": "Ονόμασε τα κύτταρα.",
    "answer": "1: Οστεοβλάστης, 2: οστεοκύτταρο, 3: οστεοκλάστης.",
    "category": "Histology"
  },
  {
    "id": "IMG_2813",
    "question": "Ονόμασε τον ιστό.",
    "answer": "Λείος μυϊκός ιστός.",
    "category": "Histology"
  },
  {
    "id": "IMG_2814",
    "question": "Ονόμασε τον ιστό και την επισημασμένη δομή.",
    "answer": "Καρδιακός μυϊκός ιστός. Η επισημασμένη δομή είναι εμβόλιμος (κλιμακωτός) δίσκος.",
    "category": "Histology"
  },
  {
    "id": "IMG_2815",
    "question": "Ονόμασε τον ιστό.",
    "answer": "Καρδιακός μυϊκός ιστός (εγκάρσια τομή).",
    "category": "Histology"
  },
  {
    "id": "IMG_2816",
    "question": "Ονόμασε τη δομή.",
    "answer": "Κύτταρο Purkinje.",
    "category": "Histology"
  },
  {
    "id": "IMG_2817",
    "question": "Ονόμασε τον ιστό.",
    "answer": "Σκελετικός γραμμωτός μυϊκός ιστός (εγκάρσια τομή).",
    "category": "Histology"
  },
  {
    "id": "IMG_2818",
    "question": "Ονόμασε τον ιστό.",
    "answer": "Σκελετικός γραμμωτός μυϊκός ιστός (επιμήκης τομή).",
    "category": "Histology"
  },
  {
    "id": "IMG_2819",
    "question": "Ονόμασε τις μαύρες ίνες.",
    "answer": "Ελαστικές ίνες.",
    "category": "Histology"
  },
  {
    "id": "IMG_2820",
    "question": "Ονόμασε τη δομή και τις τέσσερις περιοχές.",
    "answer": "Μυϊκή αρτηρία. 1: ενδοθήλιο, 2: έσω ελαστικό πέταλο, 3: μέσος χιτώνας (με πολλά λεία μυϊκά κύτταρα), 4: έξω χιτώνας.",
    "category": "Histology"
  },
  {
    "id": "IMG_2821",
    "question": "Ονόμασε τη δομή.",
    "answer": "Μυϊκή αρτηρία.",
    "category": "Histology"
  },
  {
    "id": "IMG_2822",
    "question": "Ονόμασε τη δομή.",
    "answer": "Φλέβα.",
    "category": "Histology"
  },
  {
    "id": "IMG_2823",
    "question": "Τι ιστό βλέπεις;",
    "answer": "Μυελός των οστών.",
    "category": "Histology"
  },
  {
    "id": "IMG_2824",
    "question": "Πώς ονομάζεται αυτό το κύτταρο;",
    "answer": "Μεγακαρυοκύτταρο.",
    "category": "Histology"
  },
  {
    "id": "IMG_2825",
    "question": "Ονόμασε τα κύτταρα.",
    "answer": "1: Αιμοπετάλιο, 2: ουδετερόφιλο, 3: ερυθροκύτταρο.",
    "category": "Histology"
  },
  {
    "id": "IMG_2826",
    "question": "Ονόμασε το κύτταρο.",
    "answer": "Ηωσινόφιλο.",
    "category": "Histology"
  },
  {
    "id": "IMG_2827",
    "question": "Ονόμασε τα κύτταρα.",
    "answer": "Αριστερά: βασεόφιλο. Δεξιά: ουδετερόφιλο.",
    "category": "Histology"
  },
  {
    "id": "IMG_2828",
    "question": "Ονόμασε το κύτταρο.",
    "answer": "Μονοκύτταρο.",
    "category": "Histology"
  },
  {
    "id": "IMG_2829",
    "question": "Ονόμασε το κύτταρο.",
    "answer": "Λεμφοκύτταρο.",
    "category": "Histology"
  },
  {
    "id": "IMG_2830",
    "question": "Ονόμασε το όργανο και τις ζώνες.",
    "answer": "Θύμος. Διακρίνονται ο φλοιός (σκούρα μωβ) και ο μυελός (ανοιχτόχρωμος).",
    "category": "Histology"
  },
  {
    "id": "IMG_2831",
    "question": "Πώς ονομάζεται αυτή η δομή και σε ποιο όργανο βρίσκεται;",
    "answer": "Σωμάτιο του Hassall, στον θύμο.",
    "category": "Histology"
  },
  {
    "id": "IMG_2832",
    "question": "Ονόμασε το όργανο και τις περιοχές.",
    "answer": "Λεμφαδένας. 1: κάψα, 2: φλοιός, 3: παραφλοιός, 4: μυελός.",
    "category": "Histology"
  },
  {
    "id": "IMG_2834",
    "question": "Ονόμασε το όργανο και τον τύπο των δομών 1 και 2.",
    "answer": "Λεμφαδένας. 1: δευτερογενές λεμφοζίδιο με ανοιχτόχρωμο βλαστικό κέντρο, 2: πρωτογενές λεμφοζίδιο χωρίς βλαστικό κέντρο και με πιο ομοιόμορφη, σκουρόχρωμη εμφάνιση.",
    "category": "Histology"
  },
  {
    "id": "IMG_2835",
    "question": "Ποια περιοχή του λεμφαδένα βλέπεις;",
    "answer": "Μυελός και μυελώδεις χορδές.",
    "category": "Histology"
  },
  {
    "id": "IMG_2836",
    "question": "Ονόμασε το όργανο και τις περιοχές.",
    "answer": "Σπλήνας. 1: λευκός πολφός, 2: ερυθρός πολφός.",
    "category": "Histology"
  },
  {
    "id": "IMG_2837",
    "question": "Ονόμασε τη δομή μέσα στον λευκό πολφό του σπλήνα.",
    "answer": "Κεντρική αρτηριόλη.",
    "category": "Histology"
  },
  {
    "id": "IMG_2838",
    "question": "Ονόμασε τη δομή μέσα στον ερυθρό πολφό του σπλήνα.",
    "answer": "Κολποειδές.",
    "category": "Histology"
  },
  {
    "id": "IMG_2839",
    "question": "Ονόμασε το όργανο και τις δομές.",
    "answer": "Αμυγδαλή. 1: επιθήλιο, 2: δευτερογενές λεμφοζίδιο.",
    "category": "Histology"
  },
  {
    "id": "IMG_2840",
    "question": "Τι βλέπεις;",
    "answer": "Φλοιός του εγκεφάλου.",
    "category": "Histology"
  },
  {
    "id": "IMG_2841",
    "question": "Ονόμασε τα κύτταρα.",
    "answer": "Δεξιά: πυραμιδοειδές νευρικό κύτταρο. Αριστερά: ολιγοδενδροκύτταρο.",
    "category": "Histology"
  },
  {
    "id": "IMG_2842",
    "question": "Ονόμασε το όργανο και το κύτταρο.",
    "answer": "Παρεγκεφαλίδα και κύτταρο Purkinje.",
    "category": "Histology"
  },
  {
    "id": "IMG_2844",
    "question": "Ονόμασε τη δομή και τις περιοχές.",
    "answer": "Οπίσθιο ριζικό γάγγλιο (νωτιαίο γάγγλιο). 1: σώματα νευρικών κυττάρων, 2: νευράξονες, 3: κάψα.",
    "category": "Histology"
  },
  {
    "id": "IMG_2845",
    "question": "Ονόμασε τις περιοχές του νωτιαίου γαγγλίου.",
    "answer": "1: σώμα νευρικού κυττάρου, 2: δορυφορικά κύτταρα, 3: νευράξονες.",
    "category": "Histology"
  },
  {
    "id": "IMG_2846",
    "question": "Ονόμασε το όργανο και τις περιοχές.",
    "answer": "Νωτιαίος μυελός, με λευκή ουσία (κυρίως νευράξονες) και φαιά ουσία (κυρίως σώματα νευρικών κυττάρων).",
    "category": "Histology"
  },
  {
    "id": "IMG_2847",
    "question": "Ονόμασε τη δομή και τα κύτταρα που φαίνονται σε μεγέθυνση στον νωτιαίο μυελό.",
    "answer": "Κεντρικός σωλήνας, ο οποίος επενδύεται από επενδυματικά κύτταρα και περιέχει εγκεφαλονωτιαίο υγρό (ΕΝΥ).",
    "category": "Histology"
  },
  {
    "id": "IMG_2849",
    "question": "Τι βλέπεις;",
    "answer": "Περιφερικό νεύρο στο ΠΝΣ. 1: ενδονεύριο, 2: περινεύριο, 3: επινεύριο.",
    "category": "Histology"
  },
  {
    "id": "IMG_2850",
    "question": "Τι βλέπεις και πώς ονομάζονται τα κύτταρα;",
    "answer": "Περιφερικό νεύρο στο ΠΝΣ. Τα κύτταρα είναι κύτταρα Schwann.",
    "category": "Histology"
  },
  {
    "id": "IMG_2851",
    "question": "Τι είναι αυτή η δομή;",
    "answer": "Χοριοειδές πλέγμα.",
    "category": "Histology"
  }
]
